vizably/__init__.py
vizably-0.0.1.dist-info/METADATA
vizably-0.0.1.dist-info/WHEEL
vizably-0.0.1.dist-info/top_level.txt
vizably-0.0.1.dist-info/RECORD
